em_examples/Attenuation.py
em_examples/Base.py
em_examples/BiotSavart.py
em_examples/CondUtils.py
em_examples/DCIP_overburden_PseudoSection.py
em_examples/DCLayers.py
em_examples/DCWidgetPlate2_5D.py
em_examples/DCWidgetPlate_2D.py
em_examples/DCWidgetResLayer2D.py
em_examples/DCWidgetResLayer2_5D.py
em_examples/DCWidget_Overburden_2_5D.py
em_examples/DC_Pseudosections.py
em_examples/DC_cylinder.py
em_examples/DCsphere.py
em_examples/DipoleWidget1D.py
em_examples/DipoleWidgetFD.py
em_examples/DipoleWidgetTD.py
em_examples/EMcircuit.py
em_examples/FDEM3loop.py
em_examples/FDEMDipolarfields.py
em_examples/FDEMPlanewave.py
em_examples/FDEMpipe.py
em_examples/FreqtoTime.py
em_examples/HarmonicVMDCylWidget.py
em_examples/InductionLoop.py
em_examples/InductionSphereFEM.py
em_examples/InductionSphereTEM.py
em_examples/LinearInversion.py
em_examples/Loop.py
em_examples/MT.py
em_examples/MarineCSEM1D.py
em_examples/PlanewaveWidgetFD.py
em_examples/PlanewaveWidgetTD.py
em_examples/Reflection.py
em_examples/TDEMDipolarfields.py
em_examples/TDEMGroundedSource.py
em_examples/TDEMHorizontalLoopCylWidget.py
em_examples/TDEMInductiveSource.py
em_examples/TDEMPlanewave.py
em_examples/UXO_TEM_Widget.py
em_examples/View.py
em_examples/VolumeWidget.py
em_examples/VolumeWidgetPlane.py
em_examples/__init__.py
em_examples/sphereElectrostatic_example.py
em_examples-0.0.35.dist-info/METADATA
em_examples-0.0.35.dist-info/RECORD
em_examples-0.0.35.dist-info/WHEEL
em_examples-0.0.35.dist-info/top_level.txt
tests/__init__.py
tests/test_notebooks.py
