Metadata-Version: 2.1
Name: em-examples
Version: 0.0.35
Summary: em_examples
Home-page: http://em.geosci.xyz
Author: Lindsey Heagy
Author-email: lheagy@eos.ubc.ca
License: MIT License
Download-URL: https://github.com/geoscixyz/em_examples
Keywords: geophysics,electromagnetics
Platform: Windows
Platform: Linux
Platform: Solaris
Platform: Mac OS-X
Platform: Unix
Classifier: Development Status :: 4 - Beta
Classifier: Intended Audience :: Education
Classifier: Intended Audience :: Science/Research
Classifier: License :: OSI Approved :: MIT License
Classifier: Programming Language :: Python
Classifier: Topic :: Scientific/Engineering
Classifier: Topic :: Scientific/Engineering :: Mathematics
Classifier: Topic :: Scientific/Engineering :: Physics
Classifier: Operating System :: Microsoft :: Windows
Classifier: Operating System :: POSIX
Classifier: Operating System :: Unix
Classifier: Operating System :: MacOS
Classifier: Natural Language :: English
Requires-Dist: future
Requires-Dist: numpy (>=1.7)
Requires-Dist: scipy (>=0.13)
Requires-Dist: matplotlib (>2.1.)
Requires-Dist: Pillow
Requires-Dist: requests
Requires-Dist: ipywidgets
Requires-Dist: SimPEG (>=0.4.1)
Requires-Dist: jupyter
Requires-Dist: empymod
Requires-Dist: deepdish
Requires-Dist: pymatsolver (>=0.1.2)
